{
  "$schema": "Lender Rate URLs Configuration",
  "description": "Paste the rate page URLs for each lender here. These will be used by fetch-rates script.",
  "lenders": {
    "nfcu": {
      "id": "nfcu",
      "name": "Navy Federal Credit Union",
      "rateUrl": "https://www.navyfederal.org/loans-cards/auto-loans.html",
      "enabled": true,
      "notes": "Main auto loan rates page"
    },
    "sccu": {
      "id": "sccu",
      "name": "Space Coast Credit Union",
      "rateUrl": "https://www.sccu.com/personal/consumer-rates#auto",
      "enabled": true,
      "notes": "Auto loan rates page - check for rate table"
    },
    "penfed": {
      "id": "penfed",
      "name": "Pentagon Federal Credit Union",
      "rateUrl": "https://www.penfed.org/auto",
      "enabled": true,
      "notes": "Auto rates page - check for complete term coverage (36, 48, 60, 66, 72)"
    },
    "dcu": {
      "id": "dcu",
      "name": "Digital Federal Credit Union",
      "rateUrl": "https://www.dcu.org/borrow/vehicle-loans/auto-loans.html",
      "enabled": true,
      "notes": "Vehicle loans page"
    },
    "ngfcu": {
      "id": "ngfcu",
      "name": "Northrop Grumman Federal Credit Union",
      "rateUrl": "https://www.ngfcu.us/rates/loans/auto",
      "enabled": true,
      "notes": "NEEDS UPDATE: Current URL is for credit cards. Find auto loan rates page. Missing 66-month term."
    },
    "launchcu": {
      "id": "launchcu",
      "name": "Launch Credit Union",
      "rateUrl": "https://www.launchcu.com/rates/",
      "enabled": true,
      "notes": "Main rates page - check for all terms (36-72)"
    },
    "ccufl": {
      "id": "ccufl",
      "name": "Community Credit Union of Florida",
      "rateUrl": "https://www.ccuflorida.org/home/rates/loan",
      "enabled": false,
      "notes": "NEEDS URL: Missing 72-month term in current data"
    }
  },
  "priority": [
    "nfcu",
    "dcu",
    "launchcu",
    "penfed",
    "sccu",
    "ngfcu",
    "ccufl"
  ],
  "instructions": {
    "usage": "Run: npm run fetch:rates -- --lender <lender_id> --url <url_from_this_file>",
    "example": "npm run fetch:rates -- --lender nfcu --url https://www.navyfederal.org/loans-cards/auto-loans.html",
    "update_this_file": "After verifying a URL works, update it here for documentation",
    "term_coverage": "Ensure each lender has rates for: 36, 48, 60, 66, 72 months (84 optional)",
    "known_gaps": {
      "ngfcu": "Missing 66-month term",
      "penfed": "Missing 66-month term",
      "ccufl": "Missing 72-month term",
      "sccu": "Only has 48, 66, 84 months - missing 36, 60, 72"
    }
  }
}
